setup.py
bin/dovecot-jabberd2
lib/dovecot/__init__.py
lib/dovecot.egg-info/PKG-INFO
lib/dovecot.egg-info/SOURCES.txt
lib/dovecot.egg-info/dependency_links.txt
lib/dovecot.egg-info/top_level.txt