Metadata-Version: 1.0
Name: dovecot
Version: 0.5
Summary: Library and scripts for Dovecot SASL integration
Home-page: UNKNOWN
Author: Thomas Arnett
Author-email: tom@misfeature.net
License: OSL-3.0
Platform: UNKNOWN
Classifier: Development Status :: 4 - Beta
Classifier: Intended Audience :: System Administrators
Classifier: License :: OSI Approved
Classifier: Operating System :: POSIX
Classifier: Programming Language :: Python :: 2.5
Classifier: Programming Language :: Python :: 2.6
Classifier: Programming Language :: Python :: 3.0
Classifier: Topic :: System :: Systems Administration :: Authentication/Directory
